lookup.py
setup.py
ip_lookup.egg-info/PKG-INFO
ip_lookup.egg-info/SOURCES.txt
ip_lookup.egg-info/dependency_links.txt
ip_lookup.egg-info/entry_points.txt
ip_lookup.egg-info/requires.txt
ip_lookup.egg-info/top_level.txt