Metadata-Version: 1.1
Name: ip-lookup
Version: 1.2
Summary: IP lookup via the command line
Home-page: https://github.com/dominicegginton/lookup
Author: Dominic Egginton
Author-email: dominic.egginton@gmail.com
License: MIT
Platform: any
Classifier: Environment :: Console
Classifier: Intended Audience :: Developers
Classifier: Operating System :: OS Independent
Classifier: Programming Language :: Python
